{"name":"e-construction entities","children":[{"name":"e0-construction complexes"},{"name":"e1-pavements and landscaping","children":[{"name":"e11-pavements, permanent ways","children":[{"name":"e111-rigid pavements"},{"name":"e112-rigid composite pavements"},{"name":"e113-flexible pavements"},{"name":"e114-flexible composite pavements"} ]},{"name":"e12-hard landscaping"},{"name":"e13-soft landscaping"} ]},{"name":"e2-tunnels, shafts, cuttings","children":[{"name":"e21-tunnels","children":[{"name":"e211-adits"},{"name":"e212-pilot tunnels"},{"name":"e213-immersed tube tunnels"},{"name":"e214-headings"} ]},{"name":"e22-shafts"},{"name":"e23-cuttings"} ]},{"name":"e3-embankments, retaining walls, etc_ _","children":[{"name":"e31-embankments"},{"name":"e32-retaining/protecting walls","children":[{"name":"e321-retaining walls"},{"name":"e322-protecting walls"} ]},{"name":"e33-dams","children":[{"name":"e331-embankment dams","children":[{"name":"e3311-earth dams"},{"name":"e3312-rock fill dams"},{"name":"e3313-hydraulic fill dams"} ]},{"name":"e332-gravity dams","children":[{"name":"e3321-gabion dams"},{"name":"e3322-crib dams"} ]},{"name":"e333-gravity arch dams"},{"name":"e334-arch dams"},{"name":"e335-buttress dams","children":[{"name":"e3351-arch buttress dams"},{"name":"e3352-flat slab buttress dams"},{"name":"e3353-solid head buttress dams"} ]} ]} ]},{"name":"e4-tanks, silos, etc_ _","children":[{"name":"e41-containers for gases"},{"name":"e42-tanks for liquids"},{"name":"e43-silos"} ]},{"name":"e5-bridges, viaducts","children":[{"name":"e51-bridges by material of construction","children":[{"name":"e511-steel girder bridges","children":[{"name":"e5111-steel simple beam bridges"},{"name":"e5112-steel lattice girder bridges"},{"name":"e5113-steel truss bridges"},{"name":"e5114-steel box girder bridges"} ]},{"name":"e512-concrete girder bridges","children":[{"name":"e5121-post-tensioned concrete girder bridges"},{"name":"e5122-pre-tensioned concrete girder bridges"},{"name":"e5123-concrete girder bridges with no pre-stressing"} ]},{"name":"e513-wooden bridges"},{"name":"e514-masonry bridges"},{"name":"e518-composite bridges"},{"name":"e519-other"} ]},{"name":"e52-simple span bridges"},{"name":"e53-cantilever bridges"},{"name":"e54-cable stayed bridges"},{"name":"e55-suspension bridges"},{"name":"e56-arch bridges","children":[{"name":"e561-masonry arch bridges"},{"name":"e562-concrete arch bridges"},{"name":"e563-steel arch bridges"} ]},{"name":"e57-movable bridges","children":[{"name":"e571-drawbridges"},{"name":"e572-bascules"},{"name":"e573-vertical lift bridges"},{"name":"e574-swing bridges"},{"name":"e575-retractable bridges"},{"name":"e576-floating bridges"},{"name":"e577-transporter bridges"} ]},{"name":"e58-bridges by what carried","children":[{"name":"e581-foot bridges"},{"name":"e582-bridges carrying buildings"},{"name":"e583-bridges carrying pipes or cables"} ]},{"name":"e59-bridges by geometry/scale, other types of bridges","children":[{"name":"e591-skew bridges"},{"name":"e592-curved bridges"},{"name":"e593-large span bridges"},{"name":"e594-multi-span bridges"},{"name":"e595-through-girder bridges"},{"name":"e599-other types of bridges"} ]} ]},{"name":"e6-towers, superstructures (excluding building","children":[{"name":"e61-towers"},{"name":"e62-gantries"},{"name":"e63-chimneys (free standing)"},{"name":"e64-cooling towers"},{"name":"e65-lattice towers, pylons"},{"name":"e66-masts"} ]},{"name":"e7-pipelines, ducts, cables and channels","children":[{"name":"e71-pipelines"},{"name":"e72-cables, power lines"},{"name":"e73-ducts","children":[{"name":"e731-duct networks"},{"name":"e732-jointing chambers"},{"name":"e733-cable tunnels"},{"name":"e734-cable ways"} ]},{"name":"e74-manholes, chambers"},{"name":"e75-channels, trenches, ditches, etc_ _"} ]},{"name":"e8-buildings","children":[{"name":"e81-buildings defined by height/number of storeys","children":[{"name":"e811-single storey buildings"},{"name":"e812-two storey buildings"},{"name":"e813-three storey buildings"},{"name":"e819-tall buildings, skyscrapers"} ]},{"name":"e82-buildings defined by relationship with adjacent buildings","children":[{"name":"e821-detached buildings"},{"name":"e822-semi-detached buildings"},{"name":"e823-linked/lean-to buildings"},{"name":"e824-terraces/parades"},{"name":"e825-infill buildings"},{"name":"e826-buildings constructed over something, air rights buildings"} ]},{"name":"e83-buildings defined by special form of construction","children":[{"name":"e831-structures with cable tensioned fabric roofs"},{"name":"e832-buildings with retractable roofs"},{"name":"e833-long-span, large volume buildings, supersheds"},{"name":"e834-system-built buildings, volumetric buildings"},{"name":"e835-timber framed buildings and other structures"} ]},{"name":"e84-intelligent buildings"},{"name":"e85-mobile, demountable, temporary, floating buildings","children":[{"name":"e851-mobile buildings"},{"name":"e852-demountable buildings"},{"name":"e853-temporary buildings"},{"name":"e854-floating buildings"} ]},{"name":"e86-underground buildings and other structures"},{"name":"e89-other types of buildings"} ]} ]}